{"/about/":"https://afaji.github.io/","/about.html":"https://afaji.github.io/","/resume":"https://afaji.github.io/cvshort/","/group/":"https://afaji.github.io/group.html","/groupside/":"https://afaji.github.io/groupside.html","/join/":"https://afaji.github.io/join.html","/md/":"https://afaji.github.io/markdown/","/markdown.html":"https://afaji.github.io/markdown/","/nmp/":"https://afaji.github.io/non-menu-page/","/nmp.html":"https://afaji.github.io/non-menu-page/","/profile/":"https://afaji.github.io/_pages/profile/","/profile.html":"https://afaji.github.io/_pages/profile/","/wordpress/blog-posts/":"https://afaji.github.io/year-archive/"}